{
  "_default": {
    "1": {
      "round_id": "27b4_round_1",
      "round_number": 1,
      "matches": []
    },
    "2": {
      "round_id": "27b4_round_2",
      "round_number": 2,
      "matches": []
    },
    "3": {
      "round_id": "27b4_round_3",
      "round_number": 3,
      "matches": []
    },
    "4": {
      "round_id": "27b4_round_0",
      "round_number": 0,
      "matches": [
        [
          [
            "8262abe1",
            2.0
          ],
          [
            "adb0d1f3",
            0.0
          ]
        ],
        [
          [
            "131b2f8f",
            2.0
          ],
          [
            "6aeab2e7",
            0.0
          ]
        ]
      ]
    },
    "5": {
      "round_id": "27b4_round_1",
      "round_number": 1,
      "matches": [
        [
          [
            "8262abe1",
            -1
          ],
          [
            "131b2f8f",
            -1
          ]
        ],
        [
          [
            "adb0d1f3",
            -1
          ],
          [
            "6aeab2e7",
            -1
          ]
        ]
      ]
    },
    "6": {
      "round_id": "27b4_round_2",
      "round_number": 2,
      "matches": [
        [
          [
            "8262abe1",
            -1
          ],
          [
            "6aeab2e7",
            -1
          ]
        ],
        [
          [
            "adb0d1f3",
            -1
          ],
          [
            "131b2f8f",
            -1
          ]
        ]
      ]
    }
  }
}