{"_default": {"1": {"name": "dfg", "start_date": "2021-02-02", "end_date": "2021-02-02", "description": "fg", "location": "f", "tournament_id": "540a", "round_id_list": ["540a_round_1", "540a_round_2", "540a_round_3", "540a_round_0", "540a_round_1", "540a_round_2"], "player_id_list": ["5a89fb2c", "ec78954d", "f64435bc", "bc9da502"], "current_round_number": 0, "status": "In Progress"}, "2": {"name": "xf", "start_date": "2021-02-02", "end_date": "2021-02-02", "description": "g", "location": "f", "tournament_id": "b6e6", "round_id_list": ["b6e6_round_1", "b6e6_round_2", "b6e6_round_3", "b6e6_round_0", "b6e6_round_1", "b6e6_round_2"], "player_id_list": ["68700d3a", "40df73db", "13023959", "2caaba6b"], "current_round_number": 0, "status": "In Progress"}}}